datasette_sqlite_vec_sl_tmp/__init__.py
datasette_sqlite_vec_sl_tmp-0.0.2.dist-info/METADATA
datasette_sqlite_vec_sl_tmp-0.0.2.dist-info/WHEEL
datasette_sqlite_vec_sl_tmp-0.0.2.dist-info/entry_points.txt
datasette_sqlite_vec_sl_tmp-0.0.2.dist-info/top_level.txt
datasette_sqlite_vec_sl_tmp-0.0.2.dist-info/RECORD
